[
  {
    "timestamp": "2026-07-09T23:58:06",
    "city": "Lagos",
    "lat": 6.5244,
    "lon": 3.3792,
    "aqi": 29.0,
    "category": "Good",
    "pm2_5": 5.64,
    "pm10": 11.33,
    "co": 172.67,
    "no2": 0.07,
    "so2": 0.24,
    "o3": 60.45,
    "temperature": 25.43,
    "humidity": 89.0,
    "wind_speed": 5.54,
    "pressure": 1014.0
  },
  {
    "timestamp": "2026-07-09T23:58:06",
    "city": "Abuja",
    "lat": 9.0765,
    "lon": 7.3986,
    "aqi": 35.0,
    "category": "Good",
    "pm2_5": 8.49,
    "pm10": 10.35,
    "co": 359.03,
    "no2": 2.38,
    "so2": 0.28,
    "o3": 20.64,
    "temperature": 22.18,
    "humidity": 98.0,
    "wind_speed": 1.42,
    "pressure": 1015.0
  },
  {
    "timestamp": "2026-07-09T23:58:07",
    "city": "Port Harcourt",
    "lat": 4.8156,
    "lon": 7.0498,
    "aqi": 30.0,
    "category": "Good",
    "pm2_5": 6.61,
    "pm10": 13.15,
    "co": 219.2,
    "no2": 0.09,
    "so2": 0.22,
    "o3": 63.51,
    "temperature": 23.62,
    "humidity": 95.0,
    "wind_speed": 1.79,
    "pressure": 1014.0
  },
  {
    "timestamp": "2026-07-09T23:58:07",
    "city": "Kano",
    "lat": 12.0022,
    "lon": 8.592,
    "aqi": 60.0,
    "category": "Moderate",
    "pm2_5": 16.4,
    "pm10": 19.65,
    "co": 528.35,
    "no2": 3.58,
    "so2": 0.58,
    "o3": 23.91,
    "temperature": 25.65,
    "humidity": 67.0,
    "wind_speed": 5.36,
    "pressure": 1013.0
  },
  {
    "timestamp": "2026-07-09T23:58:07",
    "city": "Ibadan",
    "lat": 7.3775,
    "lon": 3.947,
    "aqi": 29.0,
    "category": "Good",
    "pm2_5": 6.88,
    "pm10": 12.31,
    "co": 227.68,
    "no2": 1.06,
    "so2": 0.55,
    "o3": 54.2,
    "temperature": 22.68,
    "humidity": 98.0,
    "wind_speed": 1.01,
    "pressure": 1014.0
  },
  {
    "timestamp": "2026-07-09T23:58:08",
    "city": "Kaduna",
    "lat": 10.5222,
    "lon": 7.4383,
    "aqi": 28.0,
    "category": "Good",
    "pm2_5": 6.73,
    "pm10": 7.65,
    "co": 331.35,
    "no2": 2.59,
    "so2": 0.12,
    "o3": 21.31,
    "temperature": 22.2,
    "humidity": 92.0,
    "wind_speed": 1.77,
    "pressure": 1015.0
  },
  {
    "timestamp": "2026-07-09T23:58:08",
    "city": "Ogun (Ode-Remo)",
    "lat": 6.85,
    "lon": 3.6167,
    "aqi": 28.0,
    "category": "Good",
    "pm2_5": 5.42,
    "pm10": 9.96,
    "co": 157.87,
    "no2": 0.07,
    "so2": 0.22,
    "o3": 58.96,
    "temperature": 23.85,
    "humidity": 96.0,
    "wind_speed": 1.85,
    "pressure": 1014.0
  }
]